gis_mcp_client/__init__.py
gis_mcp_client/client.py
gis_mcp_client/storage.py
gis_mcp_client-0.1.1.dist-info/METADATA
gis_mcp_client-0.1.1.dist-info/WHEEL
gis_mcp_client-0.1.1.dist-info/licenses/LICENSE
gis_mcp_client-0.1.1.dist-info/RECORD
