Metadata-Version: 2.4
Name: gis-mcp-client
Version: 0.1.1
Summary: Lightweight client for connecting to GIS MCP servers to perform geospatial operations
Author: Mahdi Nazari Ashani
License: MIT License
License-File: LICENSE
Keywords: client,geospatial,gis,http,mcp,remote,sse
Classifier: Development Status :: 4 - Beta
Classifier: Intended Audience :: Developers
Classifier: License :: OSI Approved :: MIT License
Classifier: Programming Language :: Python :: 3
Classifier: Programming Language :: Python :: 3.10
Classifier: Programming Language :: Python :: 3.11
Requires-Python: >=3.10
Requires-Dist: requests>=2.31
Requires-Dist: sseclient-py>=1.8.0
Provides-Extra: dev
Requires-Dist: pytest-asyncio>=0.21.0; extra == 'dev'
Requires-Dist: pytest>=7.0.0; extra == 'dev'
